expiringsqlitedict/__init__.py
expiringsqlitedict/py.typed
expiringsqlitedict-7.0.5.dist-info/LICENSE
expiringsqlitedict-7.0.5.dist-info/WHEEL
expiringsqlitedict-7.0.5.dist-info/METADATA
expiringsqlitedict-7.0.5.dist-info/RECORD
