Metadata-Version: 2.1
Name: expiringsqlitedict
Version: 7.0.5
Summary: Persistent compressed expiring dict in Python, backed up by sqlite3 and json
Author-email: "Taylor C. Richberger" <taylor.richberger@procern.com>
Requires-Python: >= 3.6, < 4
Classifier: Development Status :: 5 - Production/Stable
Classifier: Intended Audience :: Developers
Classifier: License :: OSI Approved :: Apache Software License
Classifier: Operating System :: OS Independent
Classifier: Programming Language :: Python :: 3.6
Classifier: Programming Language :: Python :: 3.7
Classifier: Programming Language :: Python :: 3.8
Classifier: Programming Language :: Python :: 3.9
Classifier: Programming Language :: Python :: 3.10
Classifier: Programming Language :: Python :: 3.11
Classifier: Programming Language :: Python :: 3.12
Classifier: Topic :: Database :: Front-Ends
Classifier: Topic :: Software Development :: Libraries :: Python Modules
Classifier: Topic :: Software Development :: Libraries
Requires-Dist: orjson ; extra == "test"
Project-URL: documentation, https://expiringsqlitedict.readthedocs.io/
Project-URL: repository, https://github.com/ProCern/expiringsqlitedict
Provides-Extra: test
